geolabel_maker/__init__.py
geolabel_maker/_version.py
geolabel_maker/annotations.py
geolabel_maker/geolabels.py
geolabel_maker/labels.py
geolabel_maker/rasters.py
geolabel_maker/tiles.py
geolabel_maker/utils.py
geolabel_maker-0.0.1.dist-info/LICENSE.txt
geolabel_maker-0.0.1.dist-info/METADATA
geolabel_maker-0.0.1.dist-info/WHEEL
geolabel_maker-0.0.1.dist-info/entry_points.txt
geolabel_maker-0.0.1.dist-info/top_level.txt
geolabel_maker-0.0.1.dist-info/RECORD
