Metadata-Version: 2.1
Name: geolabel-maker
Version: 0.0.1
Summary: Data preparation for geospatial artificial intelligence
Home-page: https://github.com/makinacorpus/geolabel-maker/
Author: Makina Corpus
Author-email: contact@makina-corpus.com
Maintainer: Makina Corpus
License: UNKNOWN
Keywords: geospatial artificial intelligence,deep learning,convolutional neural networks,image,ground truth
Platform: UNKNOWN
Classifier: Programming Language :: Python
Classifier: Development Status :: 3 - Alpha
Classifier: License :: OSI Approved :: MIT License
Classifier: Natural Language :: English
Classifier: Operating System :: OS Independent
Classifier: Programming Language :: Python :: 3
Classifier: Topic :: Scientific/Engineering :: Artificial Intelligence
Requires-Python: >=3.6
Requires-Dist: begins
Requires-Dist: numpy
Requires-Dist: gdal2tiles
Requires-Dist: geopandas
Requires-Dist: rasterio
Requires-Dist: matplotlib
Requires-Dist: scikit-image
